.DS_Store
esl/__init__.py
esl/core.py
esl/util.py
esl/wrapper.py
EasySL-0.1.1.dist-info/LICENSE
EasySL-0.1.1.dist-info/METADATA
EasySL-0.1.1.dist-info/WHEEL
EasySL-0.1.1.dist-info/top_level.txt
EasySL-0.1.1.dist-info/RECORD
